{
  "name": "space",
  "comment": "空间",
  "fields": [
    {
      "name": "id",
      "comment": "ID",
      "type": "string",
      "length": 50,
      "primary": true
    },
    {
      "name": "project_id",
      "comment": "项目ID",
      "type": "string",
      "length": 50,
      "indexed": true
    },
    {
      "name": "parent_id",
      "comment": "父空间ID",
      "type": "string",
      "length": 50,
      "indexed": true
    },
    {
      "name": "name",
      "comment": "名称",
      "type": "string",
      "length": 50
    },
    {
      "name": "description",
      "comment": "说明",
      "type": "string",
      "length": 256
    },
    {
      "name": "disabled",
      "comment": "禁用",
      "type": "bool",
      "default": false
    },
    {
      "name": "created",
      "comment": "创建时间",
      "type": "datetime",
      "created": true
    }
  ]
}